package/__init__.py
package/data.txt
package/write.py
write_test-0.1.0.dist-info/METADATA
write_test-0.1.0.dist-info/WHEEL
write_test-0.1.0.dist-info/top_level.txt
write_test-0.1.0.dist-info/RECORD
