Metadata-Version: 2.4
Name: write_test
Version: 0.1.0
Summary: A package that writes to a personal text file.
Author: name
Requires-Python: >=3.6
Dynamic: author
Dynamic: requires-python
Dynamic: summary
